curlnagios/VERSION
curlnagios/__init__.py
curlnagios/__main__.py
curlnagios/oauth2_token.py
curlnagios/plugin_check.py
curlnagios-0.6.0.data/data/VERSION/VERSION
curlnagios-0.6.0.dist-info/DESCRIPTION.rst
curlnagios-0.6.0.dist-info/METADATA
curlnagios-0.6.0.dist-info/RECORD
curlnagios-0.6.0.dist-info/WHEEL
curlnagios-0.6.0.dist-info/entry_points.txt
curlnagios-0.6.0.dist-info/metadata.json
curlnagios-0.6.0.dist-info/top_level.txt
