Metadata-Version: 2.0
Name: curlnagios
Version: 0.6.0
Summary: curl check_http nagios plugin
Home-page: https://github.com/pablodav/curlnagios
Author: Pablo Estigarribia
Author-email: pablodav@gmail.com
License: MIT
Platform: UNKNOWN
Classifier: Development Status :: 5 - Production/Stable
Classifier: Intended Audience :: System Administrators
Classifier: License :: OSI Approved :: MIT License
Classifier: Programming Language :: Python :: 3
Classifier: Programming Language :: Python :: 3 :: Only
Classifier: Topic :: System :: Monitoring
Requires-Dist: requests (>=2.19.1)
Requires-Dist: rstcheck
